piicatcher_spacy/__init__.py
piicatcher_spacy/detectors/__init__.py
piicatcher_spacy/detectors/spacy.py
piicatcher_spacy-0.1.2.dist-info/entry_points.txt
piicatcher_spacy-0.1.2.dist-info/LICENSE
piicatcher_spacy-0.1.2.dist-info/WHEEL
piicatcher_spacy-0.1.2.dist-info/METADATA
piicatcher_spacy-0.1.2.dist-info/RECORD
